{"6iKU4zdianZrjmcXTOqQyQ==":"garden-spectacle-1.jpg","sOZACRbQlNsizQHjhNN+3A==":"garden-spectacle-1-410x360.jpg","viWkjw6WLL28vetFkV3J7g==":"basket-of-sunshine-1-457x360.jpg","qs29fO9S0+V52cJl04Pv3Q==":"basket-of-sunshine-1-60x48.png","4T/L99SgNMRF7o/53kozXg==":"wonderful.jpg","CrQsFUfOihXJV876J+uHpg==":"wonderful-410x360.jpg","FwmRftTbKk/TZof3dGnyTg==":"watercolour-wishes.jpg","CNDIIGhmy9TPXnuq3CqMyw==":"watercolour-wishes-54x48.png","MupyWhDc5Pk49ZiP70gEOQ==":"paradise-1.jpg","LAvy88857rEs9u6fPnli5Q==":"paradise-1-410x360.jpg","dmAA2bjR9Z6aWXyg/I3Tbg==":"isle-of-white-1.jpg","+9dHao9CAPMmU+vF46dtAw==":"isle-of-white-1-410x360.jpg","zxXspdMAzfR/TjsvEg9ogg==":"enchanted-garden-1.jpg","3wtef26+xcEmRQe01w2nrA==":"enchanted-garden-1-410x360.jpg","Mvt6jRQZjRtoW7u3n0/0Sw==":"celebrating-baby-girl-1.jpg","y2ZhGHBdx8WweayqboQ/xA==":"celebrating-baby-girl-1-54x48.png","4jjQe3rdl7Rke6h2KhKA5g==":"celebrating-baby-boy-1.jpg","A3qnthYwx1syeaed2f+BBw==":"celebrating-baby-boy-1-410x360.jpg","oWt7mAwU8HFb5KrkNy6YVA==":"jacqinabox-fascia1-5-800x689.jpg","55TObeYvRcHzX8uRFgCO5Q==":"background1-1.jpg","hrif2DhsySDyehmawa0PKw==":"02-1.jpg","OJSjZ+xdZsO9r4l6TRt/+g==":"03-1.jpg","BAIWnhSAJ84A0S0O/AZa+g==":"jacqinabox-fascia-1.jpg","+GXPtewMew8LLU9Kng/meQ==":"circle-logo-jacqinabox-10.jpg","RYZv2o/szatHqeeMCqHF2g==":"mbr-35.jpg","afjL16pagcUK3Qsc41WNfw==":"04-1.jpg","JHb3UaRwA1Yh5pXoXvb6Zg==":"mbr-36.jpg","PD0nqzxxD1DIsiARDiwy7A==":"mbr-37.jpg","4zrXXIdCdNCMR3sXgGhyrA==":"mbr-38.jpg","fQyNHx/xYHvXdOOUzX6yPw==":"mbr-39.jpg","2cPJqg9oXdG7b6OXFWRKUg==":"mbr-40.jpg","ySCvz9/TlD/z8vcHYQ0Qyw==":"mbr-41.jpg","ESj0Htlwns0X6xdEH7DwgA==":"dscn0406-1-640x480.jpg","rxz9OqBjsiy3VrRfUTD44g==":"wall-for-jacqinabox.jpg","I/t1mKNGqqiU7fCypW50kw==":"mbr-42.jpg","V/0LSIXB2PacuwiCYAUNfg==":"mbr-43.jpg","pkUZQ5WVn4zV0zPBy/R3HQ==":"mbr-44.jpg","9N7ROXo3M24C/7UPts4ABA==":"mbr-45.jpg","wZYBeKCRXlFvfi4AWQ731Q==":"mbr-46.jpg","TMBOZWDOdlMWcSyUoLkkBg==":"mbr-47.jpg","5LiIE6Kbu93eH/5YC1SI9w==":"mbr-48.jpg","WK5dYJxjzAVUUz6rSrzdiA==":"mbr-49.jpg","qsChocubmFVhr7Z2zNZi2Q==":"mbr-50.jpg","hibbuSULvdzLjd9n+I4TEw==":"mbr-51.jpg","AtH6Y0QyxWDNiWrvtsxLUw==":"mbr-52.jpg","h7YYDQeofai/g8BxbJ+VWQ==":"mbr-53.jpg","0fmc4+4ynx2yrudjilB/wg==":"mbr-54.jpg","K7pTe9tRLV4MxpKTv+9O6w==":"5-1-800x588.jpg","JW2NMTJMKSVHlKz9w7nzrQ==":"4-1-800x392.jpg","dDsaWXUXf3PsBTau/mQgMA==":"mbr-55.jpg","++0xzPzAvM0ClYHO1IMPEg==":"basket-of-sunshine-3-457x360.jpg","aK1Z+NYyUesT5vjcGZ5rNg==":"bright-delight-1-342x300.jpg","XVYX0l0hX3p052RjDuFpMw==":"mbr-56.jpg","kQrc5DEItd4HcHisQ+y8rg==":"citrus-splash-1-342x300.jpg","kYBH+6Vue4sRoyraIos8ng==":"slide1-1-320x180.jpg","I7LhTd52k9jOtHTnyttn8A==":"slide3-1-480x270.jpg","GGQelzVmoinYNNP87GWlkA==":"slide2-1-640x360.jpg","lnF1BSgPK6hF1zbW0p7mow==":"slide3-1-640x360.jpg","wnfw/mNPLXuvJK/sJ7P1ng==":"slide1-3-640x360.jpg","L87C4Kl6po64ogCnQjTkFA==":"slide1-1-800x450.jpg","iVlHAA1rud/Uh3SV4sSOKQ==":"basket-of-sunshine-3-761x600.jpg","tAdz5Gqigo1o0nmZlj+mOg==":"basket-of-sunshine-3-609x480.jpg","2DT/T2srPA4lXlHOgzQOvw==":"citrus-splash-1-547x480.jpg","SpcFfbV9Y/Hxfi6BYIOqVg==":"gloriou-gerberas-1-342x300.jpg","JmCNBHO2wunYPwv9gacc3A==":"gloriou-gerberas-1-547x480.jpg","m1E4v4ajLj4jKI7FN5NRdg==":"garden-spectacle-1-342x300.jpg","nUgRKgIMksHWsCrq7QXdWA==":"garden-spectacle-1-547x480.jpg","YOtdsBHLLpkp1vho+F/Xkw==":"basket-of-sunshine-4-609x480.jpg","hZRCTjji6W1HCrAe6mVDPw==":"dancing-in-daisies-1-342x300.jpg","oD+GURX+9XZKDtFF+anRQg==":"dancing-in-daisies-1-547x480.jpg","DRy1MX4oUtXWiBuv2jSZ5w==":"simply-white-1-342x300.jpg","wqfZXUtPIvOYyxxu0F/shg==":"simply-white-1-547x480.jpg","vOAPRzjr9rvfyQlgQjXrGQ==":"garden-spectacle-1-684x600.jpg","5bvH/QDzhk/ZWtSKlLEiUw==":"simply-white-1-656x576.jpg","meHW6FCyhMB7qnyrjeAT5A==":"basket-of-sunshine-4-457x360.jpg","AVb+zMHDmYO9L+r0tetlGw==":"dancing-in-daisies-2-684x600.jpg","55kpioJoKnWS8nC8qXAHFg==":"mbr-57.jpg","Hen+z1udplyKO9jBsSABHw==":"mbr-58.jpg","9Goc/r4TaqXN/oz4JyDlzw==":"boxcut2-3-600x829.jpg","cQVli5Oqc/jjIo7IWfrvyA==":"boxcut4-1-600x799.jpg","U0V5T+dJAMUdeHEHbKVHpQ==":"img-0308-2.png","zw7OyyJZMB4rZBZ0jODa6w==":"boxrose1-1.jpg","8tPlxhYzZHNR6jJk+Mj65A==":"fly-high.jpg","oKXDT1IzH5Du3uePZuWqKQ==":"logo2.png","g2hipAO6yWUEHjMYNl7XtA==":"logo.png","a1sSS21JVihTsPYUsNi2dg==":"background7.jpg","/09NNEPmf8AMYKStO1/2Vw==":"circle-logo1-1.jpg","We1seF62JmiwN3VF8VO+0w==":"mbr-11.jpg","w1Ibe37qCZOmMFOQGT2KFw==":"mbr-22.jpg","YuWWFbHWG4M+/c+wiQ15BA==":"mbr-4.jpg","QEPJPRh57h3NPO/erql39Q==":"background12.jpg","l9Pl9R2SCSgJ+mAxdPxZsw==":"background1.jpg","GSw3rD9uPHIHm6cLXOmZ8A==":"logo2-1.png","qSsWsKcmeSJptbvJXMZhVA==":"circle-logo-jacqinabox.jpg","P1NeQ/EeivIuxxLfxBjxNw==":"mbr.jpg","tePl4vZXy1MEeR1iCbu6Cw==":"boxcut4-600x799.jpg","oNXzG2WXVNZHkwB3R+Wf8g==":"boxcut7.jpg","hY+j0xXphY5MVi37QWp16w==":"boxcut8.jpg","X1fBGzW2X50qF6KT9FKWfw==":"boxcut8-1.jpg","UfZ0nklcNuuwqZkOInQLDg==":"boxcut8-2.jpg","ivCWB9qjrndPuDojlEdTVQ==":"boxcut8-3.jpg","mVdkh1dMPrcGRxLC6sQ3BQ==":"flow-1.jpg","RzkYpBX21dWzB169yawaGg==":"flow-2.jpg","ibc/KvK3n2iXZHYpUuKcEg==":"flow-3.jpg","pz3U0IvaM93AwVqhQbLYtw==":"flow-4.jpg","WOGmY4Ok73QOlMB4xIIAuQ==":"2-1.png","+Upa5RuZD+r3Ubg7cjxm6g==":"fcut3-1.jpg","U9wkQu1b6dumkeDcsRdEHA==":"fcut5.jpg","VtfDLa4N5cJMBRjeY59DNg==":"fcut7.jpg","pEC1qJoX/wPnvV7BBWRjDQ==":"fcut6.jpg","0lEshaWkFjQg3/K2S6vrRw==":"fcut11-1.jpg","8lo2m1KUQNQpEFhSub3jfw==":"fcut11-2.jpg","uoSwmEL3iw6RTp0JPTB7HQ==":"fcut12.jpg","TObPgy2WXcs4bfnu782Ozg==":"fcut-12.jpg","DPItv4EL4Kpau05JJ4uw6A==":"fcut17.jpg","vUUinjs/cuZKUPDwfnw8gQ==":"fcut17-1.jpg","5iwB3fQivfhxbusvFzIaYw==":"fcut17-2.jpg","WUDDPs9PGwezljRPEF3jVQ==":"fcut17-3.jpg","80TTT06OuEaFjFn/ozWP6g==":"fcut18-1.jpg","tZmf8z6Rvcm4/htpWFHJTw==":"fcut-18.jpg","2/BnXkdF6U6HynLF6q403w==":"fcut21.jpg","J9jsVPOnFRJebwFEahfToQ==":"fcut23-2.jpg","2eyY6tG2Qs/YRu6/3ASA9Q==":"fcut24.jpg","p4PmQtE5ng2b/+U6mqpV/A==":"img-5262.jpg","yJ7wV0o5ZXUfSeG9fvlSuw==":"dscn0061.jpg","mEPwhcRIo4PbFp37OKmtYQ==":"dscn0060.jpg","5Jn9EU3y3fiT4jLWdBMAZA==":"dscn0062.jpg","XbPFTJAP1A5k1w+ffrK7Hw==":"dscn0063.jpg","p5YzlI7exdRJD0RfGKWDkA==":"flow1.jpg","+JwXMT96ZdQx78+P1YDVlQ==":"flow-5.jpg","znrp9NqZj6dpvj3B/EyYJQ==":"img-981.jpg","cbCCDHWxOe4LOKyAtnmy8A==":"img-1361.jpg","d1fZNNOqJ6Mpe7o+jld2SQ==":"jacqinabox-fascia1-1-1400x1206.jpg","Kf8h+43fAPvhnGPr5Vvbeg==":"mbr-1.jpg","yJB0NAK7y3YQfOzriLWHeg==":"dscn0078.jpg","L/aEujnxnzIFhMTSs3UdUg==":"dscn0292.jpg","PGTMrf6eyIRk6TTSMsJTEA==":"dscn0312.jpg","BCU211qUeMwNYW1bBN27oA==":"dscn0081.jpg","h1o8wijhikbOn40eT74mIg==":"img-289.jpg","x6xDbNxx4Yvcn4Ir/k/N3A==":"img-76.jpg","jyqEXCMCZ2JRE0hxmyJB2Q==":"img-662.jpg","fVGG1achiPL7nPMmu4Bi2A==":"img-290.jpg","Gv8dXqudm69id+dsCvZW+Q==":"img-655.jpg","1QBgclUvZ2bpxq2d1NKxnQ==":"img-39.jpg","KnohKpYBtnd53pBGcA3/cQ==":"dscn0407.jpg","kmJba4CWNDl59QQTh6DaWg==":"dscn0405-1-640x480.jpg","i8q5Z/gBYgvomO8+FZyBBg==":"dscn0405-2-640x480.jpg","BCezOYZj0BNUHUvhkx2/ag==":"dscn0361.jpg","V5dp9DwKm84qJT9Mu2Z5Dw==":"dscn0361-640x480.jpg","J5VLQxjd/SYRkOCfmaFXzQ==":"dscn0381.jpg","aZ4BcT4a1ank5lRWqJY4lA==":"dscn0381-640x480.jpg","vh6DfpT9JDRTNEIQQPrGTg==":"dscn0412.jpg","Ac5cOx9KCWfkXKOAFS8yBQ==":"dscn0412-640x480.jpg","zPHXeCmoXY2rRXnCGenrRQ==":"shop1.jpg","2/dUY27JgZ3QSDhZ76hvXA==":"gopr0337.jpg","uFmc5a2OO4t0XlMKXxetBg==":"cool-room1-1.jpg","HhY+bibPTgLyASLgGXSocg==":"coolroom1.jpg","P3y8X41ouR7KLnQa4xVAXQ==":"cool-room1.jpg","13lnoN4qTRdTwyfI9Yr27w==":"cool-room2.jpg","jR6kU+Szf02QafrvglsYjQ==":"gopr0336.jpg","6GivVgQ1YkZDrZgct4g/Bw==":"img-79.jpg","bL0Er0EwRtib6LSSWeMdMw==":"cool-room2-1.jpg","z1n4YCS2cgxcchCvJf+XpA==":"gopr0339.jpg","SnKDWAfYMcSIDaehM2HMOg==":"gopr0340.jpg","ANsiq+1IGFw3g3HIiyXIoQ==":"gopr0341.jpg","69aZB5SrB3+AvN3Ijo8ITw==":"gopr0343.jpg","wZkuamL5zH29/vH5UHR+Og==":"img-663.jpg","Or7QFY7vfvbMq/ym/wjiWg==":"img-78.jpg","Y/g5YBJD8KWxXJufZ2pBJg==":"gopr0354.jpg","GRuiZl2eJ0VQZVUwNpd93w==":"img-6278.jpg","7Nzqnid7lHdFvIcuMZ+Y/w==":"dscn0043.jpg","yF/Fsc6tOqcHCh0g87Wmaw==":"fcut10-3.jpg","wnUT28IDy+r7oKVP3XoGjQ==":"box-cut1-600x778.jpg","cjNIRoNS2k+73ilv6xks0g==":"img-5263.jpg","NN9EBpPt8GJgw4g/0+IXQw==":"img-5264.jpg","0fmktWMQSYXEWPf5K5/+uw==":"img-5265.jpg","4z+v/p59VAswXGDMW2fW6Q==":"fcut-13.jpg","3zUDHuQXmeTgj/vosMFwNw==":"fcut-19.jpg","/IsY/KZLO34nQAXikjalnA==":"flow1-1.jpg","aOwcqXB9l28F8fPrBOLZsA==":"fcut2.jpg","WWtvUVLxRKYCHn0Hy9UKfg==":"fcut6-1.jpg","eojYenO2vDqLglSvploblQ==":"fcut10-1.jpg","JnGaDuunq2knl72SkP6vCQ==":"fcut16-1.jpg","iA05iM2HSIDM01wT765vJg==":"fcut21-1.jpg","pm+Z0aFGVrQ/3EtmxjzDOg==":"fcut11-3.jpg","cBt1PcqoggbsYdpXoIYGKg==":"fcut6-2.jpg","H9+ZKvsjdCN6eGwBICh7SA==":"fcut21-2.jpg","1d1JItKta92q8gkS5RmS3A==":"fcut4-1.jpg","oc2UzbqaqhFv+Ei0yAFm7A==":"snapshot21.jpg","sTHpLRciAn/2T4Nr8xi7Vg==":"dscn0043-1.jpg","k1RSDWY1VW5fVhzLZJX6Ng==":"clothes1.jpg","YvCN+fVs1sFgA9C/dlFd1w==":"mbr-2.jpg","j3e8DgLNxdmkxmapkU429w==":"mbr-5.jpg","/dQJjGIfI9WY2lAVvP65oQ==":"snapshot25.jpg","8x5xLCaOSeSctTveEAX7kA==":"snapshot30.jpg","covG7OccnG85iBW8Tn8buw==":"snapshot27.jpg","3w0LEc82uwY6Xz1Zr3SYPg==":"snapshot19.jpg","ir07QaJZYNtTSyHavOCJag==":"snapshot31.jpg","NG7N1idI/PmStU+TOGrnIg==":"snapshot18.jpg","OweVUZ5zkq2K1qHaABugsQ==":"snapshot18-640x360.jpg","xggWqMV2rn2sNGRT17DWCQ==":"snapshot28.jpg","dKsLfe6cCMQNptvK/+y08w==":"snapshot28-640x360.jpg","SJFeK5FlFaawZuAzuGssWw==":"shop1-640x480.jpg","Duw1gR9auDFTWMu+/tTCGA==":"snapshot30-640x360.jpg","SnQ1JBVwojdNUUrHAkfJAw==":"snapshot23.jpg","n2jJMAYxp4Rdd3XZp4NWzQ==":"snapshot23-640x360.jpg","eJgMPnuGClYgvhb1ptBz2Q==":"fcut2-6.jpg","7wqqGaATfUiGKoyVlzVVdA==":"fcut4-2.jpg","Ky3W48ScV+o2NMvNQ1Y6Sg==":"fcut6-3.jpg","JTYjq3HIm7OIZSHwJjmZSg==":"fcut10-2.jpg","hxPByqRAw5P8tebBNgQVOQ==":"fcut6-4.jpg","YG9YWqiRIfo2cWi3geTOoQ==":"fcut1.jpg","pPSnSI/1/DJ/kkNQXP7pEA==":"fcut3-2.jpg","hhlFCvfDvW14M0ggf+S+Hw==":"fcut5-1.jpg","n8c1S+o8he1SJCXiquIKdQ==":"fcut9.jpg","vasWDrrgl5zNR8d5XZ/gPg==":"fcut11-4.jpg","qRFSAZ5hHpX1411D7DI3Jw==":"fcut12-1.jpg","y+Ge1BSmTbJA/3c7o8XfNg==":"mbr-6.jpg","CrATkx+TQgOCohhCCIEjyg==":"12.jpg","CqSU8fglD3AEvHTCQZSMTQ==":"background4.jpg","SI68Jq11IW2byDgBshyKTw==":"boxcut9.jpg","yGMFCwrW+U5DsfNbLKNEGQ==":"snapshot16.jpg","FvfkUz598a15cm8YebkRsQ==":"mbr-17.jpg","k8chKeR8CbthxlHbHQi7Lg==":"dscn0411.jpg","fy4jKmItRFCeQ/Bz2SLGOw==":"img-281.jpg","80pzV/rj2/q18Crij1bFSg==":"fcut10-03small.jpg","8biQTIYAcowEcNUVg1Ikjw==":"teddies1.jpg","rg1KwryotxwmtctAQqkL7w==":"teddies1-1.png","LkGIfAl/xdIXbIR1DXkg6g==":"teddies1-1.jpg","/3xwOMbOHdfLjqJH/JX4Yg==":"teddies1-2.jpg","l3svI9eRdPHhAnheX1uqPg==":"teddies1-3.jpg","1ed4S2cclXT5U0yYx1fV/Q==":"teddies1-4.jpg","ja11WbtTsq9Ndp/Ldh8J/A==":"teddies1-5.jpg","DKMZiDg7Xihd/YZJqv0wKg==":"teddies1-6.jpg","y0rSnDw+6vN4lD6XZumYKg==":"teddies1-2.png","JtNQk3fe4z0apk0b+t22IA==":"bouquet1.png","Hx25fLed+B6juyQQR4lY1w==":"fcut24-1.jpg","xMryGvS3R+b0TFPICxg1WQ==":"fcut23-3.jpg","rAq7SMZ1/VXU3JZbJNRHqg==":"fcut17-4.jpg","sV2/uS3nMv3zVXzj11hUBA==":"img-7194.jpg","5ZL4wWSIFNmZwsWiAt77dA==":"mbr-18.jpg","KGql4Ux2AFGsYQI4GkFDqQ==":"background11.jpg","3mxVrxiDQXJeQF9jbh1XUA==":"bouquet1-1-800x1066.png","huxFYOq/tC7SXAGsEWZvRQ==":"boxcut2-3-600x829.jpg","Epx7V+TtkoxjfMLcyrsdZg==":"boxcut4-600x768.jpg","YYoPo6IeErnWqDC4bHxRGg==":"circle-logo-jacqinabox-8.jpg","sROlmNzaapDK2LoqO/579w==":"08.jpg","F+ohYvjcQgfBmsKR9wHxQw==":"boxcut2-4-600x829.jpg","pRZsZwr+U/osgoeM2kSyOQ==":"09.jpg","630UIZbXBwyLY1tKoHOEkA==":"10.jpg","aM6M61XYwKgz2D8ABO5tug==":"background6.jpg","z6Hugqy8vteBwM7KmWjLyw==":"mbr.jpg","PdMhXTnfigh0XDaKZAeXQA==":"02.jpg","A/+S0y5trQp4tDYML6bPeA==":"background11.jpg","l4Bx/xVkt3m31zU9IhLAsA==":"mbr-1.jpg","iXIdAUEEW/yxQRW6CauuCw==":"boxcut7-1-495x576.jpg","XCTmPCfI9gZ9O/ZU4H6a/Q==":"boxcut8-4-449x599.jpg","PXADX3VXoJs6bEKnMsqDhA==":"boxcut9-1-269x359.jpg","qFz+CxpKkwDqUdAXTPFvKw==":"fcut1-1-673x800.jpg","vInQYhVudEcUN3KZquBEAA==":"fcut5-1-604x800.jpg","F3QUTCAmnkHwfwvkW/lIKQ==":"fcut6-1-600x800.jpg","daQnAxZuRuNMUnDXtjhhAw==":"fcut7-1-586x800.jpg","GT4By9gFJsD+Z2A8owq1Tg==":"fcut-13-800x880.jpg","Xxa8VyCjxmpPMlWDB7NS9Q==":"fcut17-4-456x608.jpg","RHd4pMWr73SL4GSxuBHvsw==":"fcut-19-800x854.jpg","VhdTBzKDHtFt4VejrIYvTg==":"fcut23-4-643x799.jpg","Z55pO7KtP0h6wMRl7/FpaQ==":"flow-5-351x455.jpg","nJrKOWKW5rrWkSnfZQmPzg==":"img-982-800x1066.jpg","KHjNOvHMAiQ89Dc1uvm8CA==":"flow-6-681x800.jpg","lR24qzh2a6j89e2DXy7gcA==":"mbr-3.jpg","ci/yQOK1M8haLT/fGFYcmA==":"fcut15-1.jpg","+HXHCJ5DUf+meXcyXMMk1Q==":"fcut3-1.jpg","dXWyxiP69C9kwqnfc74H1w==":"fcut5-1.jpg","lS0dQ45KTNn17zb2ElS/oQ==":"fcut10.jpg","/jm6yTpNhRtw212j+pK8ng==":"fcut14.jpg","OPtrfMq6FKQ5ky9u787zZg==":"fcut13.jpg","JihePfzmiitvEk5YmVbIPQ==":"fcut13-1.jpg","AOHNKRRhEL0kfLjkSF+ycQ==":"fcut10-600x800.jpg","yn7bO2ynr5qjfT8WjjQldg==":"fcut16.jpg","gQ/3/d/K+nWrhuG5GsEOBw==":"mbr-4.jpg","3MNBlKhUPnBvBEP/0RRZIw==":"untitled-1.jpg","4vF2DVI3Cje7KUxyN0dAGA==":"mbr-7.jpg","Q6i8Cm9ayQO4/ri2K7+m0A==":"mbr-5.jpg","jCndhS8OAL6NtCo4w4iSuQ==":"img-1321.png","dKsZGKkM3ULIVDRA1qWadg==":"blooming-beauty-1-342x300.jpg","z6EuA9rH9/g49ELNc5st0Q==":"be-my-love-1-342x300.jpg","xBekk+Hjyj26vtxYXlPWyQ==":"celebrate-amore-1-342x300.jpg","ZOfH2QVh8aH2GgyximF8+w==":"xoxo-blush-1-342x300.jpg","vDUQEipHuxEWqF2jeAdbWw==":"snow-sparkle-1-342x300.jpg","6uArVN//jSfAoubcYMnZ9Q==":"celebrate-elegance.jpg","p3gGmN/n7K+vUTuzixH0LQ==":"enchanted-blooms.jpg","VRLd6b4Oi8W4U7H1+rjr0w==":"enchanted-evening.jpg","ZEGK854bYIbbrF5al8IbMQ==":"eternal-love.jpg","mLorHJHMyGg/lmiyKi9nAw==":"img-5264.jpg","zwTEDPG9V6JveXVoVZ1HUg==":"flow-6-351x455.jpg","fu5LX6j2dBJIrjL8hl7Ffw==":"flow-7-351x455.jpg","7DflEzW3/CLEfGHJbU3Lsw==":"flow-8-351x455.jpg","wvkKBcSx+75EWfM57shtgg==":"fcut5-2-604x800.jpg","9GVCj13/8jgsMCLHOAV3uw==":"fcut7-2-586x800.jpg","cSiguVMSejlSzoiAgmTPzA==":"img-5265.jpg","hgHXZT4FI/0/OZCi4LcJBA==":"chalk-it-kisses.jpg","hlJFQM/9Dy+1n/X8pPYvkA==":"hats-of-to-passion.jpg","jhNs67VC7wDd9R5uaNfYKg==":"heartfelt-dream.jpg","ClcQR9nRHmVCrPGhOofYag==":"fcut-19.jpg","c7KHKGCIi6STb5mEBm9+EQ==":"img-3051.png","BMk6eBTXJ/9mQAS0wakWyQ==":"chalk-it-kisses-1-342x300.jpg","cXek/K50Ogr/XkQRSf8V6Q==":"hats-of-to-passion-1-342x300.jpg","ZsLi3+IJ7Hbfwo/c1hd2Zg==":"heartfelt-dream-1-342x300.jpg","t9vOxKyyyiyVAuMgmNn7xA==":"box-cut1-600x778.jpg","812xp8oTI17fXcMTPUC9pw==":"boxcut3-1-600x701.jpg","15+Nar1o8KBJX9AASM4WFA==":"boxcut9.jpg","mShxn46uvlMfUuswOgyKsQ==":"img-5262.png","SmzfOzKB9R04js43rr8q7A==":"bright-delight.jpg","RUa979VZ8/nrjQI9aLUszw==":"fun-in-the-sun.jpg","dduAt7GAlOVT2DtCPlWAeg==":"bright-lights.jpg","GmEeIdzwupNLOszw0/2fIA==":"make-mum-smile.jpg","vBl2UDJcvGv2Uc32WooVBQ==":"blushing-beauty.jpg","Grm7zrAxmW51ud2X5w+N5A==":"celebrate-amore.jpg","HrSW4kL3OOIShiCSF/FWZQ==":"xoxo-sweetheart.jpg","3E1KaGFxYiTcLe0awDtS4A==":"chalk-it-up.jpg","+UhQojP40TuqievhK1fBjQ==":"enchanted-hope.jpg","/lrNaaIcAztrMtX4eo4Clw==":"hats-of-to-red.jpg","SFcUOIPTZcDqMVrlFbsRWA==":"heartfelt-spring.jpg","F3S03zpwkSEvGWbtExfOCA==":"sweet-sparkle.jpg","PuRH2r6Nu5YKKwW/wFpBtg==":"fcut3-2.jpg","J/wgKkUIsHfXWzub09pHfg==":"fcut7-1.jpg","O7WtaV9boKhJzlFoQrAQxQ==":"fcut7-2.jpg","wUZT9G+tQdbZvOc2QaWwaA==":"fcut10-4.jpg","JzL0Y6OsBrJGMbB8uea6hA==":"img-982.jpg","3nujqXR8uKGYGujBfdJo4g==":"dscn0406-1-64x48.png","LOM3OXRuFqtFQ/w2fiVxbg==":"dscn0405-3-640x480.jpg","Pz4BroXnua8vM75pormPrg==":"dscn0405-2-64x48.png","0ltUXrpxJ/TsDhHKRnCKLg==":"dscn0405-4-640x480.jpg","lV+Evt55aHUfgvlqBk4ZHg==":"img_e7257-517x919.jpg","cHSJigjqUEcnki91UcWq1A==":"walk%202-791x526.jpg","vj5fbZ40kCqSp6W5kIFfmQ==":"walk%206-243x432.jpg","6Br4a2lBwBtQzWs7eXH44g==":"walk%207-1455x968.jpg","lTf9fFl/BRyRR/4JygsBMw==":"artistic%20expression-342x300.jpg","lPwagMtF4XpvP1abNlfUrQ==":"glorious%20gerberas-342x300.jpg","E4mrdxgAUuMNKHLpkS+/+g==":"hanging%20banner-300x542.jpg","ebcaFoLytgoELKJcfQ7U1Q==":"hanging%20banner-300x542.jpg","Lp5ivCZIkOk4Ro6cg8zb/g==":"hanging%20banner-300x542.jpg","1os81uGXcuMQjMwi5ZC5Mg==":"shop%20front1-1920x1080.jpg","CRdRm/298ryxK92QRJLz3A==":"shop%20front1-1920x1080.jpg","vKZ0zcn0Q7N+bZoyvAYB6A==":"shop%20front1-1920x1080.jpg","JiqUh/xRuFD72FPCMEVt2g==":"shop%20front2-1920x1080.jpg","nc+6vcDOcVupHIB+duAZTA==":"inside%20shop%205-846x476.jpg","OnlYj5A5OPoVciqPXtyO7A==":"inside%20shop%205-846x476.jpg","Jc7hhelpCliKcqMjAcO8gQ==":"inside%20shop1-846x476.jpg","iKahwpaNIqEYgk99X3xGBA==":"inside%20shop3-846x476.jpg","PA+sUf2htRDgr5+CCqBT4Q==":"inside%20shop4-846x476.jpg","kjtqCmrzOrMoMnn3UqCBow==":"inside%20shop6-846x476.jpg","j2MGi+MqgRXcHHVLhmO75g==":"snapshot23-85x48.png","qb5QZBfHjwXjMaPU/e2Zjw==":"hanging%20banner-142x256.jpg","EIC9HTe19smJgC9Z/crR5Q==":"hanging%20banner-300x542.jpg","KR/StOUzNkZXR188Qe7wjQ==":"shop%20front3-1920x1080.jpg","Ah2RRiTV/V0oGA1afhfz7w==":"hanging%20banner-142x256.jpg","X+pFXFEGqa78UfzIczTt5Q==":"wreath1-2000x2998.jpg","jefmRyX+g9GqkDtds4tJwA==":"wreath2-600x800.jpg","eRLMBKjPS+BFuVY/SlnlIA==":"wreath2-1-600x800.jpg","CiRN9GVLrDChWZcH0xaLkQ==":"shop%20front3-1076x605.jpg","kmjIHlUql8D0m0KEey/GjQ==":"shop%20front3-1920x1080.jpg","tt3wkHnc7SJuxQAmQN/R2Q==":"allure%20her-342x301.jpg","L+2BN57OWLh7vFrWBypN+A==":"always%20a%20lady-342x300.jpg","GprtwUMAHjg1ydXyPxbU8Q==":"best%20friends%20forever-342x300.jpg","vCWBhrv4QdEs+DcHGw2nrQ==":"blushing%20celebration-342x300.jpg","hSmSmK5TuyKhaa2fH5SyHg==":"blushing%20roses-342x300.jpg","bb58oGoC9u43RnbCgQExxA==":"enchanted%20blooms-342x300.jpg","x8ANniR7BdK7DmTSMGmNDA==":"eternal%20love-342x300.jpg","vd7x29ppCBhBOLKE3NHYQg==":"expressions%20of%20love-342x300.jpg","f4h+dQfryeU1oLjzXtAxVA==":"fairytale%20ending-342x300.jpg","Mln3mXadI9CYSNLO4/yhPA==":"fancy%20love-342x300.jpg","rgHavdWlWGZTgSdl1xxcxA==":"first%20blush-342x300.jpg","hbj8N0euDW6i+8UTwURXfw==":"florel%20fantasy-342x300.jpg","Dz6NZUoY48WQ4ieRfXqo0w==":"heartfelt%20dream-342x300.jpg","owvEvUqQpmykInj7l4fVnQ==":"heartfelt%20romance-342x300.jpg","y+003dmBw/FrZDDkdcVzeA==":"hooray%20for%20love-342x300.jpg","m+EAaSXEmro4Q/Z6ba1DgQ==":"hopeless%20romantic-342x300.jpg","mHmX1AqjLp2apDXpIVXZ2w==":"beautiful%20day-342x300.jpg","iyvdR4J9ee+/M7CiL5gQJA==":"bright%20lights-342x300.jpg","BMR8atYsjvLNR9v+0006HQ==":"chalk%20it%20kisses-342x300.jpg","7TOp2Px0iCkd8QYWGDbeKw==":"citrus%20splash-342x300.jpg","Hckn1pte2Z7724qoL9kV8A==":"dancing%20in%20daisies-342x300.jpg","e7IOdQPrPTxqpl93VWvOxA==":"blushing%20dozen-342x300.jpg","8A8jSSOxcsYi3ngNaQy1Bw==":"bright%20delight-342x300.jpg","fxGJmf/u55NnJUDd0F/xPg==":"ciry%20chic-342x300.jpg","rbIyfomfMplW+Lcz9UWY1A==":"dreamy%20white%20dozen-342x300.jpg","IWmMhUDK3UYu3pLWwqtunQ==":"fall%20in%20love-342x300.jpg","7GiuKfh5WARECtpQPXGOKw==":"feeling%20peachy-342x300.jpg","nDW/3AZXNEMmb1/DGc6yGw==":"from%20the%20heart-342x300.jpg","b18YRMoyn6Y+gfd+Bygq1g==":"fun%20in%20the%20sun-342x300.jpg","37/IhXWGybW7NCJRB8mmXQ==":"gerbara%20brights-342x300.jpg","srGzMEQLTJfxVSW/ZhZIGg==":"jumping%20for%20joy-342x300.jpg","5CAZggSvOVUJVHdQksuGqw==":"just%20peachy-342x300.jpg","Gh0et0cQXvK6kAUi4nWqeQ==":"lavender%20wishes-342x300.jpg","zt67k9WBGZnSXyHgSU91rQ==":"lily%20devine-342x300.jpg","82UmwLFE0LoE6W0XkczLzg==":"love%20and%20laughter-342x267.jpg","jerHkQzVOmrL8i7kkg6bxQ==":"gopr0565-2000x1500.jpg","4dh9BM3+nWE9GSO1grRJLg==":"gopr0564-2000x1500.jpg","EB6QXntaSvNnX/3f1kXLGw==":"shop%20front1-864x515.jpg","RwWb9EFdVKpdwpmZw1OFoA==":"gopr0565-1-2000x1500.jpg","U1Nu7PQCv3BzyeyNY31+xQ==":"gopr0551-844x633.jpg","mSJvC8cggfK23k2Vuw6PoQ==":"gopr0550-844x633.jpg","1QxGwdL/RV6XlP5WZKn7Xw==":"clothes1-567x599.jpg","o8AUY5zSd37N2/2Iwf+fgg==":"clothes2-567x598.jpg","VQ0vO0XA4x/hUb5Rjw2ZbQ==":"gopr0561-844x633.jpg","ZRKKWzplL9mL228bu1Bt2g==":"gopr0566-844x633.jpg","E7L5SPfADnZGnE3X5ctZsA==":"gopr0557-844x633.jpg","HScAGBj6WB2KXsDYM7uxRw==":"inside%20shop1-844x475.jpg","FE5NSfH78iLM/0Vkrta3/A==":"inside%20shop1-756x425.jpg","rMj0WwSRMvHmZgTBYu06Jw==":"inside%20shop4-844x475.jpg","Uqh51cnVok5ZBCKotTqr8w==":"inside%20shop%20gift3-756x425.jpg","tEosAbeNtY6LNLdz056j7Q==":"inside%20shop%20gift4-756x425.jpg","b00b/lP42sGXpawm7IXFuQ==":"inside%20shop%20gift7-756x425.jpg","av56NTfZg+XL0n872MWBEA==":"inside%20shop%20gift6-756x425.jpg","ArHxh/1XMWz8ggeV+BzhPw==":"inside%20shop%20gift8-756x425.jpg","hfmOTSmDYmOi5Pnv3PyW+Q==":"simply%20white-342x300.jpg","4Qpp262DwZQZjwvv55vYhw==":"glorious%20gerberas-342x300.jpg","+zfXJFhB955DYV18/qHBNA==":"artistic%20expression-342x300.jpg","cVA3rsZ/90KDhiJCS0hnOA==":"grand%20gerberas-342x300.jpg","stKeYOOVeJjVOUM6gkEo5A==":"graceful%20beauty-342x300.jpg","lyLRU6UEy+KS0YCFrebceQ==":"make%20a%20wish-342x300.jpg","9o+5fcYuNIji0yNzmxim4w==":"think%20pink-342x300.jpg","chwkYiuR/xHgut8VXxmlWA==":"celebrating%20baby%20girl-342x300.jpg","/o7d9hYq5CLXx4bAha7C9w==":"celebrating%20baby%20boy-342x300.jpg","RS/h10VO2ddpep4yc3SY1w==":"fcut3-3-577x769.jpg","cGgxwDze7u3aBfhMgWpkbg==":"box-cut1-1-600x778.jpg","fI9HJGWIMZr2NV4YRbcvUQ==":"boxcut3-2-600x701.jpg","5bV6ADQDucq8kAKSM0cwUw==":"fcut5-1-604x800.jpg","XqIRedS/HDYWdhvIhS3adg==":"fcut6-1-600x800.jpg","07UpBtCfj3WhAVhuYlgJRQ==":"fcut7-3-586x778.jpg","OC8giKBn+1KHIwpFM5lUnQ==":"fcut10-5-600x767.jpg","TGP0Pm5eiHCWFVBRc0fXUw==":"fcut23-3-643x799.jpg","NQ9FTVILwPJiH9Fe8SllDw==":"fcut24-1-689x800.jpg","YOtOzmQVWmEzBLc2NkUmtg==":"flow-6-681x800.jpg","3GMwPS+yZfG0BRoxWjqF3Q==":"img-983-799x1042.jpg","JjtQZklhJX21szXOmWbh0w==":"img-1322-800x1083.png","7/1GJygAhuootFf+cDH8Yg==":"fcut23-4-643x799.jpg","I+Ki3Ach32sruhfuX8Pxww==":"fcut24-2-689x800.jpg","5cjaIT7pDe2VEj9DW2TwQg==":"flow-7-681x800.jpg","2pLWPtGzrbXrIG/1CiRPjQ==":"flow-8-681x800.jpg","9a4YaBaS6YRqcdCXSfuqDA==":"boxcut3-3-600x701.jpg","/DgAJDYnPnwXxGL3GpmG+A==":"fcut10-6-600x767.jpg","v+lPvWWQAbI9BT62jhSiJQ==":"fcut10-7-600x767.jpg","jFqUMo4qb9N9GuBjU+eQ+A==":"fcut10-8-600x767.jpg","Ce7JuAAwDbsuvE9YS5r2YA==":"fcut3-4-577x769.jpg","RMTO7G91xKqMC6O6/IdJNg==":"party%20girl-342x300.jpg","McwNJckIu/yZjnX+cI5H2A==":"sunbeam%20smiles-342x300.jpg","Ny84Fz4NRSg+5/izzhp0vw==":"inside%20shop6-854x480.jpg","U4JQmlWby1Xf58WZ1X9XTg==":"slide2-640x360.jpg","xTwA98KfVvof52R/oJgxGg==":"slide3-640x360.jpg","krjV1FHio7JJpGvTBDegAg==":"phone%20order%20for%20website1-288x432.jpg","eWsB65JqChYeGtvaQURxkA==":"phone%20order%20for%20website1-640x360.jpg","0Khb48bvyI7hHQ+qyyOT3Q==":"phone%20order%20for%20website1-85x48.png","RQkq4mXVzGfy0mBFZ+1u+A==":"hanging%20banner-2000x3613.jpg","RLdOP3dTYNYQh7zC9C0XUA==":"hanging-banner-142x255.jpg","CepCG8Wveoe2TrEjitYI4g==":"hanging%20banner-959x1734.jpg","3qD3Blm5xU3nxnKZLBoLzQ==":"hanging%20banner-959x1734.jpg","Q6wtspA2TGVINjnkWLCFFQ==":"hanging%20banner-1160x2095.jpg","YMjn2Z2rWldPJw77DQDyWA==":"hanging%20banner-360x650.jpg","6sFxm0EZL6r7SWTdSEi57A==":"hanging%20banner-2144x3873.jpg","GGUaDJFp1lpHDMa7/B9f+w==":"background4.jpg","qEPHuhoSEEzh9GwK0t2BYg==":"hanging%20bannersmall-2000x333.jpg","0OgD4M/+X5C8e0w3Zh6O7A==":"hanging%20banner-300x542.jpg","MFnSI7vM0wSmhR7EAhbOdA==":"hanging%20bannersmallupside%20down-2000x333.jpg","PoXg8WIynaZ05XuBToMl1g==":"hanging%20bannersmall-2000x333.jpg","bM79tbmtD1AeW/SV1H5TKQ==":"hanging%20bannersmall-2000x333.jpg","IH8t88VSlgCK/1Zmx2RUwQ==":"hanging%20bannersmallupside%20down-2000x333.jpg","cHva16RtbZOCTs/8LSFxRg==":"hanging-banner-143x256.jpg","dBNbyadytc2hcxyjCbS5oA==":"glorious-gerberas-342x300.jpg","WMt5Av3PLqL8J1rQTqwk0A==":"best-friends-forever-342x300.jpg","ApgbknD2wlcRwfvwDq8GNw==":"paradise-342x300.jpg","EPTspKNPU8fsg70y03sQGg==":"sweet%20thoughts-342x300.jpg","dEVwy6RhBjTdV7k+NN5Jrg==":"wonderful-342x300.jpg","MlK+U6fp5eFaUQiiSjd+Vg==":"fcut23-4-581x751.jpg","7HdQ2826GajRbl3uqe+Khw==":"fcut24-2-658x799.jpg","t4RsZ/GxJBtTx7IoyM6SXw==":"fcut3-4-255x342.jpg"}